whisply/__init__.py
whisply/app.py
whisply/app_helpers.py
whisply/cli.py
whisply/diarize_utils.py
whisply/download_utils.py
whisply/little_helper.py
whisply/models.py
whisply/output_templates.py
whisply/output_utils.py
whisply/post_correction.py
whisply/transcription.py
whisply-0.13.1.dist-info/licenses/LICENSE
whisply-0.13.1.dist-info/METADATA
whisply-0.13.1.dist-info/WHEEL
whisply-0.13.1.dist-info/entry_points.txt
whisply-0.13.1.dist-info/top_level.txt
whisply-0.13.1.dist-info/RECORD
