Metadata-Version: 2.4
Name: whisply
Version: 0.13.1
Summary: "Transcribe, translate, annotate and subtitle audio and video files with OpenAI's Whisper ... fast!"
Home-page: https://github.com/tsmdt/whisply
Author: Thomas Schmidt, Renat Shigapov
License: MIT
Requires-Python: <3.14,>=3.10
License-File: LICENSE
Requires-Dist: click==8.3.1
Requires-Dist: typer==0.20.0
Requires-Dist: matplotlib==3.10.7
Requires-Dist: faster-whisper==1.2.1
Requires-Dist: ffmpeg-python==0.2.0
Requires-Dist: optimum==1.24.0
Requires-Dist: pyannote.audio==3.4.0
Requires-Dist: whisperx==3.7.4
Requires-Dist: rich==13.7.1
Requires-Dist: torch==2.8.0
Requires-Dist: torchaudio==2.8.0
Requires-Dist: transformers==4.57.3
Requires-Dist: pytorch-lightning==2.5.4
Requires-Dist: lightning==2.5.4
Requires-Dist: validators==0.35.0
Requires-Dist: yt-dlp==2025.12.8
Provides-Extra: mlx
Requires-Dist: mlx-whisper==0.4.3; extra == "mlx"
Provides-Extra: app
Requires-Dist: gradio~=5.50.0; extra == "app"
Dynamic: license-file
